uWebSockets.cp37-win32.pyd
uWebSockets-0.14.8a1.dist-info/METADATA
uWebSockets-0.14.8a1.dist-info/WHEEL
uWebSockets-0.14.8a1.dist-info/top_level.txt
uWebSockets-0.14.8a1.dist-info/RECORD
