Metadata-Version: 2.1
Name: uWebSockets
Version: 0.14.8a1
Summary: Python Bindings for the uWebSockets library
Home-page: https://github.com/elementengineering/uWebSockets-bindings/
Author: Sam Moore
Author-email: smoore@elementengineering.com.au
License: MIT
Keywords: websockets development
Platform: UNKNOWN
Classifier: Development Status :: 3 - Alpha
Classifier: Intended Audience :: Developers
Classifier: Topic :: Software Development
Classifier: License :: OSI Approved :: MIT License
Classifier: Programming Language :: Python :: 2
Classifier: Programming Language :: Python :: 2.7
Classifier: Programming Language :: Python :: 3
Classifier: Programming Language :: Python :: 3.6
Classifier: Programming Language :: Python :: 3.7
